namekox_zookeeper_jsonrpc/__init__.py
namekox_zookeeper_jsonrpc/constants.py
namekox_zookeeper_jsonrpc/core/__init__.py
namekox_zookeeper_jsonrpc/core/mixin.py
namekox_zookeeper_jsonrpc/core/proxy.py
namekox_zookeeper_jsonrpc-0.0.8.dist-info/METADATA
namekox_zookeeper_jsonrpc-0.0.8.dist-info/WHEEL
namekox_zookeeper_jsonrpc-0.0.8.dist-info/top_level.txt
namekox_zookeeper_jsonrpc-0.0.8.dist-info/zip-safe
namekox_zookeeper_jsonrpc-0.0.8.dist-info/RECORD
