Metadata-Version: 2.1
Name: namekox-zookeeper-jsonrpc
Version: 0.0.8
Summary: namekox zookeeper jsonrpc
Home-page: https://forcemain.github.io/
Author: forcemain
License: Apache License, Version 2.0
Platform: UNKNOWN
Classifier: Programming Language :: Python
Classifier: Operating System :: MacOS :: MacOS X
Classifier: Operating System :: POSIX
Classifier: Programming Language :: Python :: 2
Classifier: Programming Language :: Python :: 2.7
Classifier: Programming Language :: Python :: 3
Classifier: Programming Language :: Python :: 3.5
Classifier: Programming Language :: Python :: 3.6
Classifier: Topic :: Internet
Classifier: Topic :: Software Development :: Libraries :: Python Modules
Classifier: Intended Audience :: Developers
Requires-Dist: namekox-zookeeper
Requires-Dist: namekox-config
Requires-Dist: namekox-context
Requires-Dist: namekox-jsonrpc
